{".class": "MypyFile", "_fullname": "optcom.components.abstract_start_comp", "is_partial_stub_package": false, "is_stub": false, "names": {".class": "SymbolTable", "AbstractComponent": {".class": "SymbolTableNode", "cross_ref": "optcom.components.abstract_component.AbstractComponent", "kind": "Gdef"}, "AbstractStartComp": {".class": "SymbolTableNode", "kind": "Gdef", "node": {".class": "TypeInfo", "_promote": null, "abstract_attributes": [], "bases": ["optcom.components.abstract_component.AbstractComponent"], "declared_metaclass": null, "defn": {".class": "ClassDef", "fullname": "optcom.components.abstract_start_comp.AbstractStartComp", "name": "AbstractStartComp", "type_vars": []}, "flags": [], "fullname": "optcom.components.abstract_start_comp.AbstractStartComp", "metaclass_type": null, "metadata": {}, "module_name": "optcom.components.abstract_start_comp", "mro": ["optcom.components.abstract_start_comp.AbstractStartComp", "optcom.components.abstract_component.AbstractComponent", "builtins.object"], "names": {".class": "SymbolTable", "__call__": {".class": "SymbolTableNode", "kind": "Mdef", "node": {".class": "FuncDef", "arg_kinds": [0, 0], "arg_names": ["self", "domain"], "flags": [], "fullname": "optcom.components.abstract_start_comp.AbstractStartComp.__call__", "name": "__call__", "type": {".class": "CallableType", "arg_kinds": [0, 0], "arg_names": ["self", "domain"], "arg_types": ["optcom.components.abstract_start_comp.AbstractStartComp", "optcom.domain.Domain"], "bound_args": [], "def_extras": {"first_arg": "self"}, "fallback": "builtins.function", "implicit": false, "is_ellipsis_args": false, "name": "__call__ of AbstractStartComp", "ret_type": {".class": "TupleType", "implicit": false, "items": [{".class": "Instance", "args": ["builtins.int"], "type_ref": "builtins.list"}, {".class": "Instance", "args": ["optcom.field.Field"], "type_ref": "builtins.list"}], "partial_fallback": {".class": "Instance", "args": [{".class": "AnyType", "missing_import_name": null, "source_any": null, "type_of_any": 6}], "type_ref": "builtins.tuple"}}, "variables": []}}}, "__init__": {".class": "SymbolTableNode", "kind": "Mdef", "node": {".class": "FuncDef", "arg_kinds": [0, 0, 0, 0, 0, 1, 1], "arg_names": ["self", "name", "default_name", "ports_type", "save", "wait", "max_nbr_pass"], "flags": [], "fullname": "optcom.components.abstract_start_comp.AbstractStartComp.__init__", "name": "__init__", "type": {".class": "CallableType", "arg_kinds": [0, 0, 0, 0, 0, 1, 1], "arg_names": ["self", "name", "default_name", "ports_type", "save", "wait", "max_nbr_pass"], "arg_types": ["optcom.components.abstract_start_comp.AbstractStartComp", "builtins.str", "builtins.str", {".class": "Instance", "args": ["builtins.int"], "type_ref": "builtins.list"}, "builtins.bool", "builtins.bool", {".class": "UnionType", "items": [{".class": "Instance", "args": ["builtins.int"], "type_ref": "builtins.list"}, {".class": "NoneType"}]}], "bound_args": [], "def_extras": {"first_arg": "self"}, "fallback": "builtins.function", "implicit": false, "is_ellipsis_args": false, "name": "__init__ of AbstractStartComp", "ret_type": {".class": "NoneType"}, "variables": []}}}}, "tuple_type": null, "type_vars": [], "typeddict_type": null}}, "Domain": {".class": "SymbolTableNode", "cross_ref": "optcom.domain.Domain", "kind": "Gdef"}, "Field": {".class": "SymbolTableNode", "cross_ref": "optcom.field.Field", "kind": "Gdef"}, "List": {".class": "SymbolTableNode", "cross_ref": "typing.List", "kind": "Gdef"}, "Optional": {".class": "SymbolTableNode", "cross_ref": "typing.Optional", "kind": "Gdef"}, "Tuple": {".class": "SymbolTableNode", "cross_ref": "typing.Tuple", "kind": "Gdef"}, "__doc__": {".class": "SymbolTableNode", "kind": "Gdef", "node": {".class": "Var", "flags": ["is_ready"], "fullname": "optcom.components.abstract_start_comp.__doc__", "name": "__doc__", "type": "builtins.str"}}, "__file__": {".class": "SymbolTableNode", "kind": "Gdef", "node": {".class": "Var", "flags": ["is_ready"], "fullname": "optcom.components.abstract_start_comp.__file__", "name": "__file__", "type": "builtins.str"}}, "__name__": {".class": "SymbolTableNode", "kind": "Gdef", "node": {".class": "Var", "flags": ["is_ready"], "fullname": "optcom.components.abstract_start_comp.__name__", "name": "__name__", "type": "builtins.str"}}, "__package__": {".class": "SymbolTableNode", "kind": "Gdef", "node": {".class": "Var", "flags": ["is_ready"], "fullname": "optcom.components.abstract_start_comp.__package__", "name": "__package__", "type": "builtins.str"}}, "cst": {".class": "SymbolTableNode", "kind": "Gdef", "node": {".class": "Var", "flags": ["is_suppressed_import", "is_ready"], "fullname": "optcom.components.abstract_start_comp.cst", "name": "cst", "type": {".class": "AnyType", "missing_import_name": "optcom.components.abstract_start_comp.cst", "source_any": null, "type_of_any": 3}}}, "util": {".class": "SymbolTableNode", "kind": "Gdef", "node": {".class": "Var", "flags": ["is_suppressed_import", "is_ready"], "fullname": "optcom.components.abstract_start_comp.util", "name": "util", "type": {".class": "AnyType", "missing_import_name": "optcom.components.abstract_start_comp.util", "source_any": null, "type_of_any": 3}}}}, "path": "/home/hibu60/Downloads/optcom_0.1.0/optcom/components/abstract_start_comp.py"}