{".class": "MypyFile", "_fullname": "optcom.components.ideal_mz", "is_partial_stub_package": false, "is_stub": false, "names": {".class": "SymbolTable", "AbstractPassComp": {".class": "SymbolTableNode", "cross_ref": "optcom.components.abstract_pass_comp.AbstractPassComp", "kind": "Gdef"}, "Array": {".class": "SymbolTableNode", "kind": "Gdef", "node": {".class": "Var", "flags": ["is_suppressed_import", "is_ready"], "fullname": "optcom.components.ideal_mz.Array", "name": "Array", "type": {".class": "AnyType", "missing_import_name": "optcom.components.ideal_mz.Array", "source_any": null, "type_of_any": 3}}}, "Callable": {".class": "SymbolTableNode", "cross_ref": "typing.Callable", "kind": "Gdef"}, "Domain": {".class": "SymbolTableNode", "cross_ref": "optcom.domain.Domain", "kind": "Gdef"}, "Field": {".class": "SymbolTableNode", "cross_ref": "optcom.field.Field", "kind": "Gdef"}, "Gaussian": {".class": "SymbolTableNode", "cross_ref": "optcom.components.gaussian.Gaussian", "kind": "Gdef"}, "IdealAmplifier": {".class": "SymbolTableNode", "cross_ref": "optcom.components.ideal_amplifier.IdealAmplifier", "kind": "Gdef"}, "IdealCombiner": {".class": "SymbolTableNode", "cross_ref": "optcom.components.ideal_combiner.IdealCombiner", "kind": "Gdef"}, "IdealDivider": {".class": "SymbolTableNode", "cross_ref": "optcom.components.ideal_divider.IdealDivider", "kind": "Gdef"}, "IdealMZ": {".class": "SymbolTableNode", "kind": "Gdef", "node": {".class": "TypeInfo", "_promote": null, "abstract_attributes": [], "bases": ["optcom.components.abstract_pass_comp.AbstractPassComp"], "declared_metaclass": null, "defn": {".class": "ClassDef", "fullname": "optcom.components.ideal_mz.IdealMZ", "name": "IdealMZ", "type_vars": []}, "flags": [], "fullname": "optcom.components.ideal_mz.IdealMZ", "metaclass_type": "abc.ABCMeta", "metadata": {}, "module_name": "optcom.components.ideal_mz", "mro": ["optcom.components.ideal_mz.IdealMZ", "optcom.components.abstract_pass_comp.AbstractPassComp", "optcom.components.abstract_component.AbstractComponent", "builtins.object"], "names": {".class": "SymbolTable", "__call__": {".class": "SymbolTableNode", "kind": "Mdef", "node": {".class": "Decorator", "func": {".class": "FuncDef", "arg_kinds": [0, 0, 0, 0], "arg_names": ["self", "domain", "ports", "fields"], "flags": ["is_decorated"], "fullname": "optcom.components.ideal_mz.IdealMZ.__call__", "name": "__call__", "type": {".class": "CallableType", "arg_kinds": [0, 0, 0, 0], "arg_names": ["self", "domain", "ports", "fields"], "arg_types": ["optcom.components.ideal_mz.IdealMZ", "optcom.domain.Domain", {".class": "Instance", "args": ["builtins.int"], "type_ref": "builtins.list"}, {".class": "Instance", "args": ["optcom.field.Field"], "type_ref": "builtins.list"}], "bound_args": [], "def_extras": {"first_arg": "self"}, "fallback": "builtins.function", "implicit": false, "is_ellipsis_args": false, "name": "__call__ of IdealMZ", "ret_type": {".class": "TupleType", "implicit": false, "items": [{".class": "Instance", "args": ["builtins.int"], "type_ref": "builtins.list"}, {".class": "Instance", "args": ["optcom.field.Field"], "type_ref": "builtins.list"}], "partial_fallback": {".class": "Instance", "args": [{".class": "AnyType", "missing_import_name": null, "source_any": null, "type_of_any": 6}], "type_ref": "builtins.tuple"}}, "variables": []}}, "is_overload": false, "var": {".class": "Var", "flags": ["is_initialized_in_class", "is_ready"], "fullname": null, "name": "__call__", "type": {".class": "AnyType", "missing_import_name": null, "source_any": null, "type_of_any": 1}}}}, "__init__": {".class": "SymbolTableNode", "kind": "Mdef", "node": {".class": "FuncDef", "arg_kinds": [0, 1, 1, 1, 1, 1, 1, 1, 1, 1, 1, 1], "arg_names": ["self", "name", "phase_shift", "loss", "extinction", "v_pi", "v_bias", "v_mod", "save", "max_nbr_pass", "pre_call_code", "post_call_code"], "flags": [], "fullname": "optcom.components.ideal_mz.IdealMZ.__init__", "name": "__init__", "type": {".class": "CallableType", "arg_kinds": [0, 1, 1, 1, 1, 1, 1, 1, 1, 1, 1, 1], "arg_names": ["self", "name", "phase_shift", "loss", "extinction", "v_pi", "v_bias", "v_mod", "save", "max_nbr_pass", "pre_call_code", "post_call_code"], "arg_types": ["optcom.components.ideal_mz.IdealMZ", "builtins.str", {".class": "UnionType", "items": [{".class": "Instance", "args": ["builtins.float"], "type_ref": "builtins.list"}, {".class": "Instance", "args": [{".class": "CallableType", "arg_kinds": [2, 4], "arg_names": [null, null], "arg_types": [{".class": "AnyType", "missing_import_name": null, "source_any": null, "type_of_any": 4}, {".class": "AnyType", "missing_import_name": null, "source_any": null, "type_of_any": 4}], "bound_args": [], "def_extras": {}, "fallback": "builtins.function", "implicit": false, "is_ellipsis_args": true, "name": null, "ret_type": {".class": "AnyType", "missing_import_name": null, "source_any": null, "type_of_any": 4}, "variables": []}], "type_ref": "builtins.list"}]}, "builtins.float", {".class": "UnionType", "items": ["builtins.float", {".class": "NoneType"}]}, {".class": "UnionType", "items": [{".class": "Instance", "args": ["builtins.float"], "type_ref": "builtins.list"}, {".class": "NoneType"}]}, {".class": "UnionType", "items": [{".class": "Instance", "args": ["builtins.float"], "type_ref": "builtins.list"}, {".class": "NoneType"}]}, {".class": "UnionType", "items": [{".class": "Instance", "args": [{".class": "CallableType", "arg_kinds": [2, 4], "arg_names": [null, null], "arg_types": [{".class": "AnyType", "missing_import_name": null, "source_any": null, "type_of_any": 4}, {".class": "AnyType", "missing_import_name": null, "source_any": null, "type_of_any": 4}], "bound_args": [], "def_extras": {}, "fallback": "builtins.function", "implicit": false, "is_ellipsis_args": true, "name": null, "ret_type": {".class": "AnyType", "missing_import_name": null, "source_any": null, "type_of_any": 4}, "variables": []}], "type_ref": "builtins.list"}, {".class": "NoneType"}]}, "builtins.bool", {".class": "UnionType", "items": [{".class": "Instance", "args": ["builtins.int"], "type_ref": "builtins.list"}, {".class": "NoneType"}]}, "builtins.str", "builtins.str"], "bound_args": [], "def_extras": {"first_arg": "self"}, "fallback": "builtins.function", "implicit": false, "is_ellipsis_args": false, "name": "__init__ of IdealMZ", "ret_type": {".class": "NoneType"}, "variables": []}}}, "_amp": {".class": "SymbolTableNode", "implicit": true, "kind": "Mdef", "node": {".class": "Var", "flags": [], "fullname": "optcom.components.ideal_mz.IdealMZ._amp", "name": "_amp", "type": "optcom.components.ideal_amplifier.IdealAmplifier"}}, "_combiner": {".class": "SymbolTableNode", "implicit": true, "kind": "Mdef", "node": {".class": "Var", "flags": [], "fullname": "optcom.components.ideal_mz.IdealMZ._combiner", "name": "_combiner", "type": "optcom.components.ideal_combiner.IdealCombiner"}}, "_divider": {".class": "SymbolTableNode", "implicit": true, "kind": "Mdef", "node": {".class": "Var", "flags": [], "fullname": "optcom.components.ideal_mz.IdealMZ._divider", "name": "_divider", "type": "optcom.components.ideal_divider.IdealDivider"}}, "_extinction": {".class": "SymbolTableNode", "implicit": true, "kind": "Mdef", "node": {".class": "Var", "flags": ["explicit_self_type", "is_ready"], "fullname": "optcom.components.ideal_mz.IdealMZ._extinction", "name": "_extinction", "type": {".class": "UnionType", "items": ["builtins.float", {".class": "NoneType"}]}}}, "_loss": {".class": "SymbolTableNode", "implicit": true, "kind": "Mdef", "node": {".class": "Var", "flags": [], "fullname": "optcom.components.ideal_mz.IdealMZ._loss", "name": "_loss", "type": "builtins.float"}}, "_nbr_instances": {".class": "SymbolTableNode", "kind": "Mdef", "node": {".class": "Var", "flags": ["is_initialized_in_class", "is_ready"], "fullname": "optcom.components.ideal_mz.IdealMZ._nbr_instances", "name": "_nbr_instances", "type": "builtins.int"}}, "_nbr_instances_with_default_name": {".class": "SymbolTableNode", "kind": "Mdef", "node": {".class": "Var", "flags": ["is_initialized_in_class", "is_ready"], "fullname": "optcom.components.ideal_mz.IdealMZ._nbr_instances_with_default_name", "name": "_nbr_instances_with_default_name", "type": "builtins.int"}}, "_phasemod_1": {".class": "SymbolTableNode", "implicit": true, "kind": "Mdef", "node": {".class": "Var", "flags": [], "fullname": "optcom.components.ideal_mz.IdealMZ._phasemod_1", "name": "_phasemod_1", "type": {".class": "AnyType", "missing_import_name": null, "source_any": null, "type_of_any": 1}}}, "_phasemod_2": {".class": "SymbolTableNode", "implicit": true, "kind": "Mdef", "node": {".class": "Var", "flags": [], "fullname": "optcom.components.ideal_mz.IdealMZ._phasemod_2", "name": "_phasemod_2", "type": {".class": "AnyType", "missing_import_name": null, "source_any": null, "type_of_any": 1}}}, "_update_phase_shift": {".class": "SymbolTableNode", "kind": "Mdef", "node": {".class": "FuncDef", "arg_kinds": [0], "arg_names": ["self"], "flags": [], "fullname": "optcom.components.ideal_mz.IdealMZ._update_phase_shift", "name": "_update_phase_shift", "type": null}}, "_v_bias": {".class": "SymbolTableNode", "implicit": true, "kind": "Mdef", "node": {".class": "Var", "flags": ["explicit_self_type", "is_ready"], "fullname": "optcom.components.ideal_mz.IdealMZ._v_bias", "name": "_v_bias", "type": {".class": "UnionType", "items": [{".class": "Instance", "args": ["builtins.float"], "type_ref": "builtins.list"}, {".class": "NoneType"}]}}}, "_v_mod": {".class": "SymbolTableNode", "implicit": true, "kind": "Mdef", "node": {".class": "Var", "flags": ["explicit_self_type", "is_ready"], "fullname": "optcom.components.ideal_mz.IdealMZ._v_mod", "name": "_v_mod", "type": {".class": "UnionType", "items": [{".class": "Instance", "args": [{".class": "CallableType", "arg_kinds": [2, 4], "arg_names": [null, null], "arg_types": [{".class": "AnyType", "missing_import_name": null, "source_any": null, "type_of_any": 4}, {".class": "AnyType", "missing_import_name": null, "source_any": null, "type_of_any": 4}], "bound_args": [], "def_extras": {}, "fallback": "builtins.function", "implicit": false, "is_ellipsis_args": true, "name": null, "ret_type": {".class": "AnyType", "missing_import_name": null, "source_any": null, "type_of_any": 4}, "variables": []}], "type_ref": "builtins.list"}, {".class": "NoneType"}]}}}, "_v_pi": {".class": "SymbolTableNode", "implicit": true, "kind": "Mdef", "node": {".class": "Var", "flags": ["explicit_self_type", "is_ready"], "fullname": "optcom.components.ideal_mz.IdealMZ._v_pi", "name": "_v_pi", "type": {".class": "UnionType", "items": [{".class": "Instance", "args": ["builtins.float"], "type_ref": "builtins.list"}, {".class": "NoneType"}]}}}, "extinction": {".class": "SymbolTableNode", "kind": "Mdef", "node": {".class": "OverloadedFuncDef", "flags": ["is_property"], "fullname": "optcom.components.ideal_mz.IdealMZ.extinction", "impl": null, "items": [{".class": "Decorator", "func": {".class": "FuncDef", "arg_kinds": [0], "arg_names": ["self"], "flags": ["is_property", "is_overload", "is_decorated"], "fullname": "optcom.components.ideal_mz.IdealMZ.extinction", "name": "extinction", "type": {".class": "CallableType", "arg_kinds": [0], "arg_names": ["self"], "arg_types": ["optcom.components.ideal_mz.IdealMZ"], "bound_args": [], "def_extras": {"first_arg": "self"}, "fallback": "builtins.function", "implicit": false, "is_ellipsis_args": false, "name": "extinction of IdealMZ", "ret_type": {".class": "UnionType", "items": ["builtins.float", {".class": "NoneType"}]}, "variables": []}}, "is_overload": true, "var": {".class": "Var", "flags": ["is_initialized_in_class", "is_property", "is_settable_property", "is_ready"], "fullname": null, "name": "extinction", "type": {".class": "CallableType", "arg_kinds": [0], "arg_names": ["self"], "arg_types": ["optcom.components.ideal_mz.IdealMZ"], "bound_args": [], "def_extras": {"first_arg": "self"}, "fallback": "builtins.function", "implicit": false, "is_ellipsis_args": false, "name": "extinction of IdealMZ", "ret_type": {".class": "UnionType", "items": ["builtins.float", {".class": "NoneType"}]}, "variables": []}}}, {".class": "Decorator", "func": {".class": "FuncDef", "arg_kinds": [0, 0], "arg_names": ["self", "extinction"], "flags": ["is_decorated"], "fullname": "optcom.components.ideal_mz.IdealMZ.extinction", "name": "extinction", "type": {".class": "CallableType", "arg_kinds": [0, 0], "arg_names": ["self", "extinction"], "arg_types": ["optcom.components.ideal_mz.IdealMZ", {".class": "UnionType", "items": ["builtins.float", {".class": "NoneType"}]}], "bound_args": [], "def_extras": {"first_arg": "self"}, "fallback": "builtins.function", "implicit": false, "is_ellipsis_args": false, "name": "extinction of IdealMZ", "ret_type": {".class": "NoneType"}, "variables": []}}, "is_overload": false, "var": {".class": "Var", "flags": [], "fullname": null, "name": "extinction", "type": null}}], "type": {".class": "Overloaded", "items": [{".class": "CallableType", "arg_kinds": [0], "arg_names": ["self"], "arg_types": ["optcom.components.ideal_mz.IdealMZ"], "bound_args": [], "def_extras": {"first_arg": "self"}, "fallback": "builtins.function", "implicit": false, "is_ellipsis_args": false, "name": "extinction of IdealMZ", "ret_type": {".class": "UnionType", "items": ["builtins.float", {".class": "NoneType"}]}, "variables": []}]}}}, "loss": {".class": "SymbolTableNode", "kind": "Mdef", "node": {".class": "OverloadedFuncDef", "flags": ["is_property"], "fullname": "optcom.components.ideal_mz.IdealMZ.loss", "impl": null, "items": [{".class": "Decorator", "func": {".class": "FuncDef", "arg_kinds": [0], "arg_names": ["self"], "flags": ["is_property", "is_overload", "is_decorated"], "fullname": "optcom.components.ideal_mz.IdealMZ.loss", "name": "loss", "type": {".class": "CallableType", "arg_kinds": [0], "arg_names": ["self"], "arg_types": ["optcom.components.ideal_mz.IdealMZ"], "bound_args": [], "def_extras": {"first_arg": "self"}, "fallback": "builtins.function", "implicit": false, "is_ellipsis_args": false, "name": "loss of IdealMZ", "ret_type": "builtins.float", "variables": []}}, "is_overload": true, "var": {".class": "Var", "flags": ["is_initialized_in_class", "is_property", "is_settable_property", "is_ready"], "fullname": null, "name": "loss", "type": {".class": "CallableType", "arg_kinds": [0], "arg_names": ["self"], "arg_types": ["optcom.components.ideal_mz.IdealMZ"], "bound_args": [], "def_extras": {"first_arg": "self"}, "fallback": "builtins.function", "implicit": false, "is_ellipsis_args": false, "name": "loss of IdealMZ", "ret_type": "builtins.float", "variables": []}}}, {".class": "Decorator", "func": {".class": "FuncDef", "arg_kinds": [0, 0], "arg_names": ["self", "loss"], "flags": ["is_decorated"], "fullname": "optcom.components.ideal_mz.IdealMZ.loss", "name": "loss", "type": {".class": "CallableType", "arg_kinds": [0, 0], "arg_names": ["self", "loss"], "arg_types": ["optcom.components.ideal_mz.IdealMZ", "builtins.float"], "bound_args": [], "def_extras": {"first_arg": "self"}, "fallback": "builtins.function", "implicit": false, "is_ellipsis_args": false, "name": "loss of IdealMZ", "ret_type": {".class": "NoneType"}, "variables": []}}, "is_overload": false, "var": {".class": "Var", "flags": [], "fullname": null, "name": "loss", "type": null}}], "type": {".class": "Overloaded", "items": [{".class": "CallableType", "arg_kinds": [0], "arg_names": ["self"], "arg_types": ["optcom.components.ideal_mz.IdealMZ"], "bound_args": [], "def_extras": {"first_arg": "self"}, "fallback": "builtins.function", "implicit": false, "is_ellipsis_args": false, "name": "loss of IdealMZ", "ret_type": "builtins.float", "variables": []}]}}}, "phase_shift": {".class": "SymbolTableNode", "kind": "Mdef", "node": {".class": "OverloadedFuncDef", "flags": ["is_property"], "fullname": "optcom.components.ideal_mz.IdealMZ.phase_shift", "impl": null, "items": [{".class": "Decorator", "func": {".class": "FuncDef", "arg_kinds": [0], "arg_names": ["self"], "flags": ["is_property", "is_overload", "is_decorated"], "fullname": "optcom.components.ideal_mz.IdealMZ.phase_shift", "name": "phase_shift", "type": {".class": "CallableType", "arg_kinds": [0], "arg_names": ["self"], "arg_types": ["optcom.components.ideal_mz.IdealMZ"], "bound_args": [], "def_extras": {"first_arg": "self"}, "fallback": "builtins.function", "implicit": false, "is_ellipsis_args": false, "name": "phase_shift of IdealMZ", "ret_type": {".class": "UnionType", "items": [{".class": "Instance", "args": ["builtins.float"], "type_ref": "builtins.list"}, {".class": "Instance", "args": [{".class": "CallableType", "arg_kinds": [2, 4], "arg_names": [null, null], "arg_types": [{".class": "AnyType", "missing_import_name": null, "source_any": null, "type_of_any": 4}, {".class": "AnyType", "missing_import_name": null, "source_any": null, "type_of_any": 4}], "bound_args": [], "def_extras": {}, "fallback": "builtins.function", "implicit": false, "is_ellipsis_args": true, "name": null, "ret_type": {".class": "AnyType", "missing_import_name": null, "source_any": null, "type_of_any": 4}, "variables": []}], "type_ref": "builtins.list"}]}, "variables": []}}, "is_overload": true, "var": {".class": "Var", "flags": ["is_initialized_in_class", "is_property", "is_settable_property", "is_ready"], "fullname": null, "name": "phase_shift", "type": {".class": "CallableType", "arg_kinds": [0], "arg_names": ["self"], "arg_types": ["optcom.components.ideal_mz.IdealMZ"], "bound_args": [], "def_extras": {"first_arg": "self"}, "fallback": "builtins.function", "implicit": false, "is_ellipsis_args": false, "name": "phase_shift of IdealMZ", "ret_type": {".class": "UnionType", "items": [{".class": "Instance", "args": ["builtins.float"], "type_ref": "builtins.list"}, {".class": "Instance", "args": [{".class": "CallableType", "arg_kinds": [2, 4], "arg_names": [null, null], "arg_types": [{".class": "AnyType", "missing_import_name": null, "source_any": null, "type_of_any": 4}, {".class": "AnyType", "missing_import_name": null, "source_any": null, "type_of_any": 4}], "bound_args": [], "def_extras": {}, "fallback": "builtins.function", "implicit": false, "is_ellipsis_args": true, "name": null, "ret_type": {".class": "AnyType", "missing_import_name": null, "source_any": null, "type_of_any": 4}, "variables": []}], "type_ref": "builtins.list"}]}, "variables": []}}}, {".class": "Decorator", "func": {".class": "FuncDef", "arg_kinds": [0, 0], "arg_names": ["self", "phase_shift"], "flags": ["is_decorated"], "fullname": "optcom.components.ideal_mz.IdealMZ.phase_shift", "name": "phase_shift", "type": {".class": "CallableType", "arg_kinds": [0, 0], "arg_names": ["self", "phase_shift"], "arg_types": ["optcom.components.ideal_mz.IdealMZ", {".class": "UnionType", "items": [{".class": "Instance", "args": ["builtins.float"], "type_ref": "builtins.list"}, {".class": "Instance", "args": [{".class": "CallableType", "arg_kinds": [2, 4], "arg_names": [null, null], "arg_types": [{".class": "AnyType", "missing_import_name": null, "source_any": null, "type_of_any": 4}, {".class": "AnyType", "missing_import_name": null, "source_any": null, "type_of_any": 4}], "bound_args": [], "def_extras": {}, "fallback": "builtins.function", "implicit": false, "is_ellipsis_args": true, "name": null, "ret_type": {".class": "AnyType", "missing_import_name": null, "source_any": null, "type_of_any": 4}, "variables": []}], "type_ref": "builtins.list"}]}], "bound_args": [], "def_extras": {"first_arg": "self"}, "fallback": "builtins.function", "implicit": false, "is_ellipsis_args": false, "name": "phase_shift of IdealMZ", "ret_type": {".class": "NoneType"}, "variables": []}}, "is_overload": false, "var": {".class": "Var", "flags": [], "fullname": null, "name": "phase_shift", "type": null}}], "type": {".class": "Overloaded", "items": [{".class": "CallableType", "arg_kinds": [0], "arg_names": ["self"], "arg_types": ["optcom.components.ideal_mz.IdealMZ"], "bound_args": [], "def_extras": {"first_arg": "self"}, "fallback": "builtins.function", "implicit": false, "is_ellipsis_args": false, "name": "phase_shift of IdealMZ", "ret_type": {".class": "UnionType", "items": [{".class": "Instance", "args": ["builtins.float"], "type_ref": "builtins.list"}, {".class": "Instance", "args": [{".class": "CallableType", "arg_kinds": [2, 4], "arg_names": [null, null], "arg_types": [{".class": "AnyType", "missing_import_name": null, "source_any": null, "type_of_any": 4}, {".class": "AnyType", "missing_import_name": null, "source_any": null, "type_of_any": 4}], "bound_args": [], "def_extras": {}, "fallback": "builtins.function", "implicit": false, "is_ellipsis_args": true, "name": null, "ret_type": {".class": "AnyType", "missing_import_name": null, "source_any": null, "type_of_any": 4}, "variables": []}], "type_ref": "builtins.list"}]}, "variables": []}]}}}, "v_bias": {".class": "SymbolTableNode", "kind": "Mdef", "node": {".class": "OverloadedFuncDef", "flags": ["is_property"], "fullname": "optcom.components.ideal_mz.IdealMZ.v_bias", "impl": null, "items": [{".class": "Decorator", "func": {".class": "FuncDef", "arg_kinds": [0], "arg_names": ["self"], "flags": ["is_property", "is_overload", "is_decorated"], "fullname": "optcom.components.ideal_mz.IdealMZ.v_bias", "name": "v_bias", "type": {".class": "CallableType", "arg_kinds": [0], "arg_names": ["self"], "arg_types": ["optcom.components.ideal_mz.IdealMZ"], "bound_args": [], "def_extras": {"first_arg": "self"}, "fallback": "builtins.function", "implicit": false, "is_ellipsis_args": false, "name": "v_bias of IdealMZ", "ret_type": {".class": "UnionType", "items": [{".class": "Instance", "args": ["builtins.float"], "type_ref": "builtins.list"}, {".class": "NoneType"}]}, "variables": []}}, "is_overload": true, "var": {".class": "Var", "flags": ["is_initialized_in_class", "is_property", "is_settable_property", "is_ready"], "fullname": null, "name": "v_bias", "type": {".class": "CallableType", "arg_kinds": [0], "arg_names": ["self"], "arg_types": ["optcom.components.ideal_mz.IdealMZ"], "bound_args": [], "def_extras": {"first_arg": "self"}, "fallback": "builtins.function", "implicit": false, "is_ellipsis_args": false, "name": "v_bias of IdealMZ", "ret_type": {".class": "UnionType", "items": [{".class": "Instance", "args": ["builtins.float"], "type_ref": "builtins.list"}, {".class": "NoneType"}]}, "variables": []}}}, {".class": "Decorator", "func": {".class": "FuncDef", "arg_kinds": [0, 0], "arg_names": ["self", "v_bias"], "flags": ["is_decorated"], "fullname": "optcom.components.ideal_mz.IdealMZ.v_bias", "name": "v_bias", "type": {".class": "CallableType", "arg_kinds": [0, 0], "arg_names": ["self", "v_bias"], "arg_types": ["optcom.components.ideal_mz.IdealMZ", {".class": "UnionType", "items": [{".class": "Instance", "args": ["builtins.float"], "type_ref": "builtins.list"}, {".class": "NoneType"}]}], "bound_args": [], "def_extras": {"first_arg": "self"}, "fallback": "builtins.function", "implicit": false, "is_ellipsis_args": false, "name": "v_bias of IdealMZ", "ret_type": {".class": "NoneType"}, "variables": []}}, "is_overload": false, "var": {".class": "Var", "flags": [], "fullname": null, "name": "v_bias", "type": null}}], "type": {".class": "Overloaded", "items": [{".class": "CallableType", "arg_kinds": [0], "arg_names": ["self"], "arg_types": ["optcom.components.ideal_mz.IdealMZ"], "bound_args": [], "def_extras": {"first_arg": "self"}, "fallback": "builtins.function", "implicit": false, "is_ellipsis_args": false, "name": "v_bias of IdealMZ", "ret_type": {".class": "UnionType", "items": [{".class": "Instance", "args": ["builtins.float"], "type_ref": "builtins.list"}, {".class": "NoneType"}]}, "variables": []}]}}}, "v_mod": {".class": "SymbolTableNode", "kind": "Mdef", "node": {".class": "OverloadedFuncDef", "flags": ["is_property"], "fullname": "optcom.components.ideal_mz.IdealMZ.v_mod", "impl": null, "items": [{".class": "Decorator", "func": {".class": "FuncDef", "arg_kinds": [0], "arg_names": ["self"], "flags": ["is_property", "is_overload", "is_decorated"], "fullname": "optcom.components.ideal_mz.IdealMZ.v_mod", "name": "v_mod", "type": {".class": "CallableType", "arg_kinds": [0], "arg_names": ["self"], "arg_types": ["optcom.components.ideal_mz.IdealMZ"], "bound_args": [], "def_extras": {"first_arg": "self"}, "fallback": "builtins.function", "implicit": false, "is_ellipsis_args": false, "name": "v_mod of IdealMZ", "ret_type": {".class": "UnionType", "items": [{".class": "Instance", "args": [{".class": "CallableType", "arg_kinds": [2, 4], "arg_names": [null, null], "arg_types": [{".class": "AnyType", "missing_import_name": null, "source_any": null, "type_of_any": 4}, {".class": "AnyType", "missing_import_name": null, "source_any": null, "type_of_any": 4}], "bound_args": [], "def_extras": {}, "fallback": "builtins.function", "implicit": false, "is_ellipsis_args": true, "name": null, "ret_type": {".class": "AnyType", "missing_import_name": null, "source_any": null, "type_of_any": 4}, "variables": []}], "type_ref": "builtins.list"}, {".class": "NoneType"}]}, "variables": []}}, "is_overload": true, "var": {".class": "Var", "flags": ["is_initialized_in_class", "is_property", "is_settable_property", "is_ready"], "fullname": null, "name": "v_mod", "type": {".class": "CallableType", "arg_kinds": [0], "arg_names": ["self"], "arg_types": ["optcom.components.ideal_mz.IdealMZ"], "bound_args": [], "def_extras": {"first_arg": "self"}, "fallback": "builtins.function", "implicit": false, "is_ellipsis_args": false, "name": "v_mod of IdealMZ", "ret_type": {".class": "UnionType", "items": [{".class": "Instance", "args": [{".class": "CallableType", "arg_kinds": [2, 4], "arg_names": [null, null], "arg_types": [{".class": "AnyType", "missing_import_name": null, "source_any": null, "type_of_any": 4}, {".class": "AnyType", "missing_import_name": null, "source_any": null, "type_of_any": 4}], "bound_args": [], "def_extras": {}, "fallback": "builtins.function", "implicit": false, "is_ellipsis_args": true, "name": null, "ret_type": {".class": "AnyType", "missing_import_name": null, "source_any": null, "type_of_any": 4}, "variables": []}], "type_ref": "builtins.list"}, {".class": "NoneType"}]}, "variables": []}}}, {".class": "Decorator", "func": {".class": "FuncDef", "arg_kinds": [0, 0], "arg_names": ["self", "v_mod"], "flags": ["is_decorated"], "fullname": "optcom.components.ideal_mz.IdealMZ.v_mod", "name": "v_mod", "type": {".class": "CallableType", "arg_kinds": [0, 0], "arg_names": ["self", "v_mod"], "arg_types": ["optcom.components.ideal_mz.IdealMZ", {".class": "UnionType", "items": [{".class": "Instance", "args": [{".class": "CallableType", "arg_kinds": [2, 4], "arg_names": [null, null], "arg_types": [{".class": "AnyType", "missing_import_name": null, "source_any": null, "type_of_any": 4}, {".class": "AnyType", "missing_import_name": null, "source_any": null, "type_of_any": 4}], "bound_args": [], "def_extras": {}, "fallback": "builtins.function", "implicit": false, "is_ellipsis_args": true, "name": null, "ret_type": {".class": "AnyType", "missing_import_name": null, "source_any": null, "type_of_any": 4}, "variables": []}], "type_ref": "builtins.list"}, {".class": "NoneType"}]}], "bound_args": [], "def_extras": {"first_arg": "self"}, "fallback": "builtins.function", "implicit": false, "is_ellipsis_args": false, "name": "v_mod of IdealMZ", "ret_type": {".class": "NoneType"}, "variables": []}}, "is_overload": false, "var": {".class": "Var", "flags": [], "fullname": null, "name": "v_mod", "type": null}}], "type": {".class": "Overloaded", "items": [{".class": "CallableType", "arg_kinds": [0], "arg_names": ["self"], "arg_types": ["optcom.components.ideal_mz.IdealMZ"], "bound_args": [], "def_extras": {"first_arg": "self"}, "fallback": "builtins.function", "implicit": false, "is_ellipsis_args": false, "name": "v_mod of IdealMZ", "ret_type": {".class": "UnionType", "items": [{".class": "Instance", "args": [{".class": "CallableType", "arg_kinds": [2, 4], "arg_names": [null, null], "arg_types": [{".class": "AnyType", "missing_import_name": null, "source_any": null, "type_of_any": 4}, {".class": "AnyType", "missing_import_name": null, "source_any": null, "type_of_any": 4}], "bound_args": [], "def_extras": {}, "fallback": "builtins.function", "implicit": false, "is_ellipsis_args": true, "name": null, "ret_type": {".class": "AnyType", "missing_import_name": null, "source_any": null, "type_of_any": 4}, "variables": []}], "type_ref": "builtins.list"}, {".class": "NoneType"}]}, "variables": []}]}}}, "v_pi": {".class": "SymbolTableNode", "kind": "Mdef", "node": {".class": "OverloadedFuncDef", "flags": ["is_property"], "fullname": "optcom.components.ideal_mz.IdealMZ.v_pi", "impl": null, "items": [{".class": "Decorator", "func": {".class": "FuncDef", "arg_kinds": [0], "arg_names": ["self"], "flags": ["is_property", "is_overload", "is_decorated"], "fullname": "optcom.components.ideal_mz.IdealMZ.v_pi", "name": "v_pi", "type": {".class": "CallableType", "arg_kinds": [0], "arg_names": ["self"], "arg_types": ["optcom.components.ideal_mz.IdealMZ"], "bound_args": [], "def_extras": {"first_arg": "self"}, "fallback": "builtins.function", "implicit": false, "is_ellipsis_args": false, "name": "v_pi of IdealMZ", "ret_type": {".class": "UnionType", "items": [{".class": "Instance", "args": ["builtins.float"], "type_ref": "builtins.list"}, {".class": "NoneType"}]}, "variables": []}}, "is_overload": true, "var": {".class": "Var", "flags": ["is_initialized_in_class", "is_property", "is_settable_property", "is_ready"], "fullname": null, "name": "v_pi", "type": {".class": "CallableType", "arg_kinds": [0], "arg_names": ["self"], "arg_types": ["optcom.components.ideal_mz.IdealMZ"], "bound_args": [], "def_extras": {"first_arg": "self"}, "fallback": "builtins.function", "implicit": false, "is_ellipsis_args": false, "name": "v_pi of IdealMZ", "ret_type": {".class": "UnionType", "items": [{".class": "Instance", "args": ["builtins.float"], "type_ref": "builtins.list"}, {".class": "NoneType"}]}, "variables": []}}}, {".class": "Decorator", "func": {".class": "FuncDef", "arg_kinds": [0, 0], "arg_names": ["self", "v_pi"], "flags": ["is_decorated"], "fullname": "optcom.components.ideal_mz.IdealMZ.v_pi", "name": "v_pi", "type": {".class": "CallableType", "arg_kinds": [0, 0], "arg_names": ["self", "v_pi"], "arg_types": ["optcom.components.ideal_mz.IdealMZ", {".class": "UnionType", "items": [{".class": "Instance", "args": ["builtins.float"], "type_ref": "builtins.list"}, {".class": "NoneType"}]}], "bound_args": [], "def_extras": {"first_arg": "self"}, "fallback": "builtins.function", "implicit": false, "is_ellipsis_args": false, "name": "v_pi of IdealMZ", "ret_type": {".class": "NoneType"}, "variables": []}}, "is_overload": false, "var": {".class": "Var", "flags": [], "fullname": null, "name": "v_pi", "type": null}}], "type": {".class": "Overloaded", "items": [{".class": "CallableType", "arg_kinds": [0], "arg_names": ["self"], "arg_types": ["optcom.components.ideal_mz.IdealMZ"], "bound_args": [], "def_extras": {"first_arg": "self"}, "fallback": "builtins.function", "implicit": false, "is_ellipsis_args": false, "name": "v_pi of IdealMZ", "ret_type": {".class": "UnionType", "items": [{".class": "Instance", "args": ["builtins.float"], "type_ref": "builtins.list"}, {".class": "NoneType"}]}, "variables": []}]}}}}, "tuple_type": null, "type_vars": [], "typeddict_type": null}}, "IdealPhaseMod": {".class": "SymbolTableNode", "cross_ref": "optcom.components.ideal_phase_mod.IdealPhaseMod", "kind": "Gdef"}, "Layout": {".class": "SymbolTableNode", "cross_ref": "optcom.layout.Layout", "kind": "Gdef"}, "List": {".class": "SymbolTableNode", "cross_ref": "typing.List", "kind": "Gdef"}, "Optional": {".class": "SymbolTableNode", "cross_ref": "typing.Optional", "kind": "Gdef"}, "Sequence": {".class": "SymbolTableNode", "cross_ref": "typing.Sequence", "kind": "Gdef"}, "Tuple": {".class": "SymbolTableNode", "cross_ref": "typing.Tuple", "kind": "Gdef"}, "Union": {".class": "SymbolTableNode", "cross_ref": "typing.Union", "kind": "Gdef"}, "__doc__": {".class": "SymbolTableNode", "kind": "Gdef", "node": {".class": "Var", "flags": ["is_ready"], "fullname": "optcom.components.ideal_mz.__doc__", "name": "__doc__", "type": "builtins.str"}}, "__file__": {".class": "SymbolTableNode", "kind": "Gdef", "node": {".class": "Var", "flags": ["is_ready"], "fullname": "optcom.components.ideal_mz.__file__", "name": "__file__", "type": "builtins.str"}}, "__name__": {".class": "SymbolTableNode", "kind": "Gdef", "node": {".class": "Var", "flags": ["is_ready"], "fullname": "optcom.components.ideal_mz.__name__", "name": "__name__", "type": "builtins.str"}}, "__package__": {".class": "SymbolTableNode", "kind": "Gdef", "node": {".class": "Var", "flags": ["is_ready"], "fullname": "optcom.components.ideal_mz.__package__", "name": "__package__", "type": "builtins.str"}}, "call_decorator": {".class": "SymbolTableNode", "cross_ref": "optcom.components.abstract_pass_comp.call_decorator", "kind": "Gdef"}, "cst": {".class": "SymbolTableNode", "cross_ref": "optcom.utils.constants", "kind": "Gdef"}, "default_name": {".class": "SymbolTableNode", "kind": "Gdef", "node": {".class": "Var", "flags": ["is_ready"], "fullname": "optcom.components.ideal_mz.default_name", "name": "default_name", "type": "builtins.str"}}, "er": {".class": "SymbolTableNode", "kind": "Gdef", "node": {".class": "Var", "flags": ["is_ready"], "fullname": "optcom.components.ideal_mz.er", "name": "er", "type": "builtins.float"}}, "i": {".class": "SymbolTableNode", "kind": "Gdef", "node": {".class": "Var", "flags": [], "fullname": "optcom.components.ideal_mz.i", "name": "i", "type": "builtins.int"}}, "loss": {".class": "SymbolTableNode", "kind": "Gdef", "node": {".class": "Var", "flags": ["is_ready"], "fullname": "optcom.components.ideal_mz.loss", "name": "loss", "type": "builtins.float"}}, "lt": {".class": "SymbolTableNode", "kind": "Gdef", "node": {".class": "Var", "flags": ["is_ready"], "fullname": "optcom.components.ideal_mz.lt", "name": "lt", "type": "optcom.layout.Layout"}}, "math": {".class": "SymbolTableNode", "cross_ref": "math", "kind": "Gdef"}, "mz": {".class": "SymbolTableNode", "kind": "Gdef", "node": {".class": "Var", "flags": ["is_ready"], "fullname": "optcom.components.ideal_mz.mz", "name": "mz", "type": "optcom.components.ideal_mz.IdealMZ"}}, "phase_shift": {".class": "SymbolTableNode", "kind": "Gdef", "node": {".class": "Var", "flags": [], "fullname": "optcom.components.ideal_mz.phase_shift", "name": "phase_shift", "type": {".class": "Instance", "args": ["builtins.float"], "type_ref": "builtins.list"}}}, "phase_shift_s": {".class": "SymbolTableNode", "kind": "Gdef", "node": {".class": "Var", "flags": ["is_ready"], "fullname": "optcom.components.ideal_mz.phase_shift_s", "name": "phase_shift_s", "type": {".class": "Instance", "args": ["builtins.float"], "type_ref": "builtins.list"}}}, "phase_shifts": {".class": "SymbolTableNode", "kind": "Gdef", "node": {".class": "Var", "flags": ["is_ready"], "fullname": "optcom.components.ideal_mz.phase_shifts", "name": "phase_shifts", "type": {".class": "Instance", "args": [{".class": "Instance", "args": ["builtins.float"], "type_ref": "builtins.list"}], "type_ref": "builtins.list"}}}, "plot": {".class": "SymbolTableNode", "cross_ref": "optcom.utils.plot", "kind": "Gdef"}, "plot_titles": {".class": "SymbolTableNode", "kind": "Gdef", "node": {".class": "Var", "flags": ["is_ready"], "fullname": "optcom.components.ideal_mz.plot_titles", "name": "plot_titles", "type": {".class": "Instance", "args": ["builtins.str"], "type_ref": "builtins.list"}}}, "pulse": {".class": "SymbolTableNode", "kind": "Gdef", "node": {".class": "Var", "flags": ["is_ready"], "fullname": "optcom.components.ideal_mz.pulse", "name": "pulse", "type": "optcom.components.gaussian.Gaussian"}}, "random": {".class": "SymbolTableNode", "cross_ref": "random", "kind": "Gdef"}, "random_phase": {".class": "SymbolTableNode", "kind": "Gdef", "node": {".class": "Var", "flags": ["is_ready"], "fullname": "optcom.components.ideal_mz.random_phase", "name": "random_phase", "type": "builtins.float"}}, "random_phase_bis": {".class": "SymbolTableNode", "kind": "Gdef", "node": {".class": "Var", "flags": ["is_ready"], "fullname": "optcom.components.ideal_mz.random_phase_bis", "name": "random_phase_bis", "type": "builtins.float"}}, "spectral_phase": {".class": "SymbolTableNode", "cross_ref": "optcom.utils.utilities_user.spectral_phase", "kind": "Gdef"}, "spectral_power": {".class": "SymbolTableNode", "cross_ref": "optcom.utils.utilities_user.spectral_power", "kind": "Gdef"}, "temp_phase": {".class": "SymbolTableNode", "kind": "Gdef", "node": {".class": "Var", "flags": [], "fullname": "optcom.components.ideal_mz.temp_phase", "name": "temp_phase", "type": {".class": "Instance", "args": ["builtins.float"], "type_ref": "builtins.list"}}}, "temporal_phase": {".class": "SymbolTableNode", "cross_ref": "optcom.utils.utilities_user.temporal_phase", "kind": "Gdef"}, "temporal_power": {".class": "SymbolTableNode", "cross_ref": "optcom.utils.utilities_user.temporal_power", "kind": "Gdef"}, "util": {".class": "SymbolTableNode", "cross_ref": "optcom.utils.utilities", "kind": "Gdef"}, "v_bias": {".class": "SymbolTableNode", "kind": "Gdef", "node": {".class": "Var", "flags": ["is_ready"], "fullname": "optcom.components.ideal_mz.v_bias", "name": "v_bias", "type": {".class": "Instance", "args": ["builtins.float"], "type_ref": "builtins.list"}}}, "v_mod": {".class": "SymbolTableNode", "kind": "Gdef", "node": {".class": "Var", "flags": ["is_ready"], "fullname": "optcom.components.ideal_mz.v_mod", "name": "v_mod", "type": {".class": "Instance", "args": [{".class": "CallableType", "arg_kinds": [2, 4], "arg_names": [null, null], "arg_types": [{".class": "AnyType", "missing_import_name": null, "source_any": null, "type_of_any": 4}, {".class": "AnyType", "missing_import_name": null, "source_any": null, "type_of_any": 4}], "bound_args": [], "def_extras": {}, "fallback": "builtins.function", "implicit": false, "is_ellipsis_args": true, "name": null, "ret_type": {".class": "AnyType", "missing_import_name": null, "source_any": null, "type_of_any": 4}, "variables": []}], "type_ref": "builtins.list"}}}, "v_pi": {".class": "SymbolTableNode", "kind": "Gdef", "node": {".class": "Var", "flags": ["is_ready"], "fullname": "optcom.components.ideal_mz.v_pi", "name": "v_pi", "type": {".class": "Instance", "args": ["builtins.float"], "type_ref": "builtins.list"}}}, "x_datas": {".class": "SymbolTableNode", "kind": "Gdef", "node": {".class": "Var", "flags": ["is_ready"], "fullname": "optcom.components.ideal_mz.x_datas", "name": "x_datas", "type": {".class": "Instance", "args": [{".class": "AnyType", "missing_import_name": "optcom.components.ideal_mz.Array", "source_any": null, "type_of_any": 3}], "type_ref": "builtins.list"}}}, "y_datas": {".class": "SymbolTableNode", "kind": "Gdef", "node": {".class": "Var", "flags": ["is_ready"], "fullname": "optcom.components.ideal_mz.y_datas", "name": "y_datas", "type": {".class": "Instance", "args": [{".class": "AnyType", "missing_import_name": "optcom.components.ideal_mz.Array", "source_any": null, "type_of_any": 3}], "type_ref": "builtins.list"}}}}, "path": "optcom/components/ideal_mz.py"}