{".class": "MypyFile", "_fullname": "canlse", "is_partial_stub_package": false, "is_stub": false, "names": {".class": "SymbolTable", "ANLSE": {".class": "SymbolTableNode", "kind": "Gdef", "node": {".class": "Var", "flags": ["is_suppressed_import"], "fullname": "canlse.ANLSE", "name": "ANLSE", "type": {".class": "AnyType", "missing_import_name": "canlse.ANLSE", "source_any": null, "type_of_any": 3}}}, "AbstractCNLSE": {".class": "SymbolTableNode", "kind": "Gdef", "node": {".class": "Var", "flags": ["is_suppressed_import"], "fullname": "canlse.AbstractCNLSE", "name": "AbstractCNLSE", "type": {".class": "AnyType", "missing_import_name": "canlse.AbstractCNLSE", "source_any": null, "type_of_any": 3}}}, "CANLSE": {".class": "SymbolTableNode", "kind": "Gdef", "node": {".class": "TypeInfo", "_promote": null, "abstract_attributes": [], "bases": ["builtins.object"], "declared_metaclass": null, "defn": {".class": "ClassDef", "fullname": "canlse.CANLSE", "name": "CANLSE", "type_vars": []}, "flags": ["fallback_to_any"], "fullname": "canlse.CANLSE", "metaclass_type": null, "metadata": {}, "module_name": "canlse", "mro": ["canlse.CANLSE", "builtins.object"], "names": {".class": "SymbolTable", "__init__": {".class": "SymbolTableNode", "kind": "Mdef", "node": {".class": "FuncDef", "arg_kinds": [0, 1, 1, 1, 1, 1, 1, 1, 1, 1, 1, 1, 1, 1, 1, 1, 1, 1, 1, 1, 1], "arg_names": ["self", "nbr_fibers", "alpha", "beta", "gamma", "kappa", "sigma", "sigma_cross", "eta", "raman_coeff", "center_omega", "SPM", "XPM", "FWM", "SS", "RS", "approx_type", "c2c_spacing", "core_radius", "V", "n_0"], "flags": [], "fullname": "canlse.CANLSE.__init__", "name": "__init__", "type": {".class": "CallableType", "arg_kinds": [0, 1, 1, 1, 1, 1, 1, 1, 1, 1, 1, 1, 1, 1, 1, 1, 1, 1, 1, 1, 1], "arg_names": ["self", "nbr_fibers", "alpha", "beta", "gamma", "kappa", "sigma", "sigma_cross", "eta", "raman_coeff", "center_omega", "SPM", "XPM", "FWM", "SS", "RS", "approx_type", "c2c_spacing", "core_radius", "V", "n_0"], "arg_types": ["canlse.CANLSE", "builtins.int", {".class": "Instance", "args": [{".class": "UnionType", "items": [{".class": "Instance", "args": ["builtins.float"], "type_ref": "builtins.list"}, {".class": "NoneType"}]}], "type_ref": "builtins.list"}, {".class": "Instance", "args": [{".class": "UnionType", "items": [{".class": "Instance", "args": ["builtins.float"], "type_ref": "builtins.list"}, {".class": "NoneType"}]}], "type_ref": "builtins.list"}, {".class": "Instance", "args": [{".class": "UnionType", "items": ["builtins.float", {".class": "NoneType"}]}], "type_ref": "builtins.list"}, {".class": "Instance", "args": [{".class": "UnionType", "items": [{".class": "Instance", "args": [{".class": "Instance", "args": ["builtins.float"], "type_ref": "builtins.list"}], "type_ref": "builtins.list"}, {".class": "NoneType"}]}], "type_ref": "builtins.list"}, {".class": "Instance", "args": ["builtins.float"], "type_ref": "builtins.list"}, {".class": "Instance", "args": [{".class": "Instance", "args": ["builtins.float"], "type_ref": "builtins.list"}], "type_ref": "builtins.list"}, "builtins.float", "builtins.float", {".class": "UnionType", "items": ["builtins.float", {".class": "NoneType"}]}, "builtins.bool", "builtins.bool", "builtins.bool", "builtins.bool", "builtins.bool", "builtins.int", "builtins.float", "builtins.float", "builtins.float", "builtins.float"], "bound_args": [], "def_extras": {"first_arg": "self"}, "fallback": "builtins.function", "implicit": false, "is_ellipsis_args": false, "name": "__init__ of CANLSE", "ret_type": {".class": "NoneType"}, "variables": []}}}}, "tuple_type": null, "type_vars": [], "typeddict_type": null}}, "List": {".class": "SymbolTableNode", "cross_ref": "typing.List", "kind": "Gdef"}, "Optional": {".class": "SymbolTableNode", "cross_ref": "typing.Optional", "kind": "Gdef"}, "__doc__": {".class": "SymbolTableNode", "kind": "Gdef", "node": {".class": "Var", "flags": [], "fullname": "canlse.__doc__", "name": "__doc__", "type": "builtins.str"}}, "__file__": {".class": "SymbolTableNode", "kind": "Gdef", "node": {".class": "Var", "flags": [], "fullname": "canlse.__file__", "name": "__file__", "type": "builtins.str"}}, "__name__": {".class": "SymbolTableNode", "kind": "Gdef", "node": {".class": "Var", "flags": [], "fullname": "canlse.__name__", "name": "__name__", "type": "builtins.str"}}, "__package__": {".class": "SymbolTableNode", "kind": "Gdef", "node": {".class": "Var", "flags": [], "fullname": "canlse.__package__", "name": "__package__", "type": "builtins.str"}}, "cst": {".class": "SymbolTableNode", "kind": "Gdef", "node": {".class": "Var", "flags": ["is_suppressed_import"], "fullname": "canlse.cst", "name": "cst", "type": {".class": "AnyType", "missing_import_name": "canlse.cst", "source_any": null, "type_of_any": 3}}}, "util": {".class": "SymbolTableNode", "kind": "Gdef", "node": {".class": "Var", "flags": ["is_suppressed_import"], "fullname": "canlse.util", "name": "util", "type": {".class": "AnyType", "missing_import_name": "canlse.util", "source_any": null, "type_of_any": 3}}}}, "path": "optcom/equations/canlse.py"}